verilog/hardware/processor/verilog/instruction_mem_ram.v
/*
	Authored 2018-2019, Ryan Voo.
	All rights reserved.
	Redistribution and use in source and binary forms, with or without
	modification, are permitted provided that the following conditions
	are met:
	*	Redistributions of source code must retain the above
		copyright notice, this list of conditions and the following
		disclaimer.
	*	Redistributions in binary form must reproduce the above
		copyright notice, this list of conditions and the following
		disclaimer in the documentation and/or other materials
		provided with the distribution.
	*	Neither the name of the author nor the names of its
		contributors may be used to endorse or promote products
		derived from this software without specific prior written
		permission.
	THIS SOFTWARE IS PROVIDED BY THE COPYRIGHT HOLDERS AND CONTRIBUTORS
	"AS IS" AND ANY EXPRESS OR IMPLIED WARRANTIES, INCLUDING, BUT NOT
	LIMITED TO, THE IMPLIED WARRANTIES OF MERCHANTABILITY AND FITNESS
	FOR A PARTICULAR PURPOSE ARE DISCLAIMED. IN NO EVENT SHALL THE
	COPYRIGHT OWNER OR CONTRIBUTORS BE LIABLE FOR ANY DIRECT, INDIRECT,
	INCIDENTAL, SPECIAL, EXEMPLARY, OR CONSEQUENTIAL DAMAGES (INCLUDING,
	BUT NOT LIMITED TO, PROCUREMENT OF SUBSTITUTE GOODS OR SERVICES;
	LOSS OF USE, DATA, OR PROFITS; OR BUSINESS INTERRUPTION) HOWEVER
	CAUSED AND ON ANY THEORY OF LIABILITY, WHETHER IN CONTRACT, STRICT
	LIABILITY, OR TORT (INCLUDING NEGLIGENCE OR OTHERWISE) ARISING IN
	ANY WAY OUT OF THE USE OF THIS SOFTWARE, EVEN IF ADVISED OF THE
	POSSIBILITY OF SUCH DAMAGE.
*/



/*
 *	RISC-V instruction memory
 */



module instruction_memory(clk, addr, out);
  input clk;
	input [31:0]		addr;
	output [31:0]		out;

	/*
	 *	Size the instruction memory.
	 *
	 *	(Bad practice: The constant should be a `define).
	 */
	reg [31:0]		instruction_memory[0:2**12-1];

	/*
	 *	According to the "iCE40 SPRAM Usage Guide" (TN1314 Version 1.0), page 5:
	 *
	 *		"SB_SPRAM256KA RAM does not support initialization through device configuration."
	 *
	 *	The only way to have an initializable memory is to use the Block RAM.
	 *	This uses Yosys's support for nonzero initial values:
	 *
	 *		https://github.com/YosysHQ/yosys/commit/0793f1b196df536975a044a4ce53025c81d00c7f
	 *
	 *	Rather than using this simulation construct (`initial`),
	 *	the design should instead use a reset signal going to
	 *	modules in the design.
	 */
	initial begin
		/*
		 *	read from "program.hex" and store the instructions in instruction memory
		 */
		$readmemh("verilog/program.hex",instruction_memory);
	end

  always @(posedge clk) begin
    out <= {instruction_memory[addr >> 2][31:16], instruction_memory[addr >> 2][15:0]};
	
endmodule

verilog/hardware/processor/simulation/instruction_sim.v
module top();
	reg clk = 0;

  wire[31:0] instruction_o;
  reg[31:0] addr;

  instruction_memory instructionmem_inst(
    .clk(clk),
    .addr(addr),
    .out(instruction_o)
  );

//simulation
always
 #0.5 clk = ~clk;

initial begin
	$dumpfile ("instruction_mem.vcd");
 	$dumpvars;
  addr = 32'b0;
  
  #5
  
 addr = addr + 32'b100;
  
  #5
    
  addr = addr + 32'b100;
  
  #5
    
  addr = addr + 32'b100;
  
  #5
    
  addr = addr + 32'b100;
  
  #5
    
  addr = addr + 32'b100;
  
  #5
  $finish;
  
end
  
endmodule

verilog/hardware/processor/simulation/instruction_mem.vcd
$date
	Fri Jun  4 12:45:52 2021
$end
$version
	Icarus Verilog
$end
$timescale
	1s
$end
$scope module top $end
$var wire 32 ! instruction_o [31:0] $end
$var reg 32 " addr [31:0] $end
$var reg 1 # clk $end
$scope module instructionmem_inst $end
$var wire 32 $ addr [31:0] $end
$var wire 1 # clk $end
$var reg 32 % out [31:0] $end
$upscope $end
$upscope $end
$enddefinitions $end
#0
$dumpvars
bx %
b0 $
0#
b0 "
bx !
$end
#1
b10011 !
b10011 %
1#
#2
0#
#3
1#
#4
0#
#5
b1000100110111 !
b1000100110111 %
1#
b100 "
b100 $
#6
0#
#7
1#
#8
0#
#9
1#
#10
0#
b1000 "
b1000 $
#11
b10000000000000010000000100010011 !
b10000000000000010000000100010011 %
1#
#12
0#
#13
1#
#14
0#
#15
b1111000000000000000001101111 !
b1111000000000000000001101111 %
1#
b1100 "
b1100 $
#16
0#
#17
1#
#18
0#
#19
1#
#20
0#
b10000 "
b10000 $
#21
b11111101000000010000000100010011 !
b11111101000000010000000100010011 %
1#
#22
0#
#23
1#
#24
0#
#25
b10000100010010011000100011 !
b10000100010010011000100011 %
1#
b10100 "
b10100 $
